django_i18next-0.1.3.dist-info/WHEEL
django_i18next-0.1.3.dist-info/metadata.json
django_i18next-0.1.3.dist-info/RECORD
django_i18next-0.1.3.dist-info/DESCRIPTION.rst
django_i18next-0.1.3.dist-info/top_level.txt
django_i18next-0.1.3.dist-info/METADATA
i18next/models.py
i18next/settings.py
i18next/defaults.py
i18next/conf.py
i18next/apps.py
i18next/__init__.py
i18next/tests/base.py
i18next/tests/helpers.py
i18next/tests/__init__.py
i18next/tests/test_core.py
i18next/templatetags/i18next.py
i18next/templatetags/__init__.py
